gymnasium_quadruped/__init__.py
gymnasium_quadruped/assets/unitree_a1/LICENSE
gymnasium_quadruped/assets/unitree_a1/README.md
gymnasium_quadruped/assets/unitree_a1/a1.png
gymnasium_quadruped/assets/unitree_a1/a1.xml
gymnasium_quadruped/assets/unitree_a1/assets/calf.obj
gymnasium_quadruped/assets/unitree_a1/assets/hip.obj
gymnasium_quadruped/assets/unitree_a1/assets/thigh.obj
gymnasium_quadruped/assets/unitree_a1/assets/thigh_mirror.obj
gymnasium_quadruped/assets/unitree_a1/assets/trunk.obj
gymnasium_quadruped/assets/unitree_a1/assets/trunk_A1.png
gymnasium_quadruped/assets/unitree_a1/scene.xml
gymnasium_quadruped/envs/__init__.py
gymnasium_quadruped/envs/a1.py
gymnasium_quadruped/envs/ant.py
gymnasium_quadruped-0.0.1.dist-info/LICENSE
gymnasium_quadruped-0.0.1.dist-info/WHEEL
gymnasium_quadruped-0.0.1.dist-info/METADATA
gymnasium_quadruped-0.0.1.dist-info/RECORD
