Metadata-Version: 2.1
Name: gymnasium-quadruped
Version: 0.0.1
Summary: Gymnasium environment for training quadruped legged robots
Home-page: https://github.com/dtch1997/gymnasium-quadruped
Author: Daniel CH Tan
Author-email: fdtch1997@users.noreply.github.com
Requires-Python: >=3.8,<4.0
Classifier: Programming Language :: Python :: 3
Classifier: Programming Language :: Python :: 3.8
Classifier: Programming Language :: Python :: 3.9
Classifier: Programming Language :: Python :: 3.10
Classifier: Programming Language :: Python :: 3.11
Requires-Dist: gymnasium[mujoco] (>=0.28.1,<0.29.0)
Requires-Dist: numpy (>=1.24.3,<2.0.0)
Project-URL: Documentation, https://dtch1997.github.io/gymnasium-quadruped/
Project-URL: Repository, https://github.com/dtch1997/gymnasium-quadruped
